{
  "publicPath": "/_nuxt/",
  "all": [
    "../server/index.spa.html",
    "../server/index.ssr.html",
    "06873ae.js",
    "10f7f16.js",
    "18b436d.js",
    "27076f4.js",
    "296531b.js",
    "2c6fca8.js",
    "4356888.js",
    "4e4af3e.js",
    "52eda56.js",
    "5692b44.js",
    "5b856a5.js",
    "61bca87.js",
    "63fee22.js",
    "665e510.js",
    "6fe4976.js",
    "908cb9e.js",
    "9606e1b.js",
    "9708540.js",
    "97d676a.js",
    "9f43c5f.js",
    "LICENSES",
    "a07282e.js",
    "a9693bd.js",
    "a9d4700.js",
    "bbfc829.js",
    "bdeb4aa.js",
    "bfb8431.js",
    "c372057.js",
    "c482ac6.js",
    "c9ad686.js",
    "c9ebafb.js",
    "d8f626b.js",
    "dcbced5.js",
    "de1af1d.js",
    "e20e1a4.js",
    "ed9b438.js",
    "fd4c8d3.js",
    "ffa1495.js",
    "fonts/remixicon.5cb99e6.eot",
    "fonts/remixicon.8d09fa1.woff",
    "fonts/remixicon.90668f6.woff2",
    "fonts/remixicon.f2616f5.ttf",
    "img/join_process_1.29bba9b.png",
    "img/join_process_2.8a6bdd2.png",
    "img/remixicon.9cedd21.svg"
  ],
  "initial": [
    "a07282e.js",
    "bfb8431.js",
    "06873ae.js",
    "9606e1b.js"
  ],
  "async": [
    "10f7f16.js",
    "18b436d.js",
    "27076f4.js",
    "296531b.js",
    "2c6fca8.js",
    "4356888.js",
    "4e4af3e.js",
    "52eda56.js",
    "5692b44.js",
    "5b856a5.js",
    "61bca87.js",
    "63fee22.js",
    "665e510.js",
    "6fe4976.js",
    "908cb9e.js",
    "9708540.js",
    "97d676a.js",
    "9f43c5f.js",
    "a9693bd.js",
    "a9d4700.js",
    "bbfc829.js",
    "bdeb4aa.js",
    "c372057.js",
    "c482ac6.js",
    "c9ad686.js",
    "c9ebafb.js",
    "d8f626b.js",
    "dcbced5.js",
    "de1af1d.js",
    "e20e1a4.js",
    "ed9b438.js",
    "fd4c8d3.js",
    "ffa1495.js"
  ],
  "modules": {
    "11167217": [
      28
    ],
    "12759943": [
      34
    ],
    "14442841": [
      28
    ],
    "15259443": [
      2,
      40,
      42,
      41,
      43,
      46
    ],
    "18059056": [
      2,
      40,
      42,
      41,
      43,
      46
    ],
    "33127052": [
      34
    ],
    "38270057": [
      2,
      40,
      42,
      41,
      43,
      46
    ],
    "39014167": [
      28
    ],
    "40691912": [
      28
    ],
    "44817192": [
      27
    ],
    "46147460": [
      2,
      40,
      42,
      41,
      43,
      46
    ],
    "46826280": [
      28
    ],
    "49684994": [
      2,
      40,
      42,
      41,
      43,
      46
    ],
    "59682272": [
      2,
      40,
      42,
      41,
      43,
      46
    ],
    "60075314": [
      36
    ],
    "62018338": [
      2,
      40,
      42,
      41,
      43,
      46
    ],
    "64529168": [
      18
    ],
    "67357415": [
      24
    ],
    "73602209": [
      2,
      40,
      42,
      41,
      43,
      46
    ],
    "73685702": [
      5,
      27,
      9,
      34
    ],
    "77996478": [
      14
    ],
    "95038576": [
      2,
      40,
      42,
      41,
      43,
      46
    ],
    "97273580": [
      2,
      40,
      42,
      41,
      43,
      46
    ],
    "98064186": [
      2,
      40,
      42,
      41,
      43,
      46
    ],
    "6c4cf3b5": [
      2,
      40,
      42,
      41,
      43,
      46
    ],
    "a7aa4aa6": [
      28
    ],
    "67d147ba": [
      28
    ],
    "163c3a4a": [
      18
    ],
    "18b8a1e2": [
      2,
      40,
      42,
      41,
      43,
      46
    ],
    "0a327a1b": [
      28
    ],
    "9b7d5df0": [
      28
    ],
    "4dad351a": [
      28
    ],
    "68fd86bd": [
      28
    ],
    "c40d8594": [
      28
    ],
    "1e96a8ba": [
      2,
      40,
      42,
      41,
      43,
      46
    ],
    "17a41fe1": [
      28
    ],
    "270e5d2a": [
      28
    ],
    "d94d9442": [
      28
    ],
    "6ecf79a8": [
      28
    ],
    "1eb164e7": [
      2,
      40,
      42,
      41,
      43,
      46
    ],
    "57b545f0": [
      2,
      40,
      42,
      41,
      43,
      46
    ],
    "3c8c0635": [
      2,
      40,
      42,
      41,
      43,
      46
    ],
    "a711b4b8": [
      2,
      40,
      42,
      41,
      43,
      46
    ],
    "669a7fd8": [
      28
    ],
    "50eca0f5": [
      28
    ],
    "2423f005": [
      28
    ],
    "2a63564a": [
      2,
      40,
      42,
      41,
      43,
      46
    ],
    "2f99d9b6": [
      28
    ],
    "599fdca9": [
      28
    ],
    "39f7ab2e": [
      28
    ],
    "7ce0439e": [
      28
    ],
    "11555bd4": [
      2,
      40,
      42,
      41,
      43,
      46
    ],
    "f8611540": [
      28
    ],
    "1ccfbef8": [
      2,
      40,
      42,
      41,
      43,
      46
    ],
    "c3774780": [
      28
    ],
    "3dbc19a1": [
      28
    ],
    "cbc92750": [
      28
    ],
    "aaf7cafc": [
      2,
      40,
      42,
      41,
      43,
      46
    ],
    "f567c7ca": [
      28
    ],
    "c7929c1e": [
      28
    ],
    "34171c8f": [
      28
    ],
    "3d119a56": [
      28
    ],
    "786a9f08": [
      28
    ],
    "b6b5f5ca": [
      28
    ],
    "121accb0": [
      18
    ],
    "770df233": [
      28
    ],
    "5e1f92a5": [
      28
    ],
    "500f3dd7": [
      2,
      40,
      42,
      41,
      43,
      46
    ],
    "734a4a88": [
      2,
      40,
      42,
      41,
      43,
      46
    ],
    "159a2632": [
      28
    ],
    "6aaca450": [
      28
    ],
    "17d3c836": [
      28
    ],
    "5f82faab": [
      2,
      40,
      42,
      41,
      43,
      46
    ],
    "aeaab2fa": [
      28
    ],
    "cc58a380": [
      28
    ],
    "648d0cb3": [
      2,
      40,
      42,
      41,
      43,
      46
    ],
    "2ab43012": [
      2,
      40,
      42,
      41,
      43,
      46
    ],
    "549332d4": [
      2,
      40,
      42,
      41,
      43,
      46
    ],
    "ca1eb15e": [
      28
    ],
    "3352ce64": [
      28
    ],
    "00b994c6": [
      28
    ],
    "486f0dd6": [
      28
    ],
    "1e7bf0e2": [
      28
    ],
    "1bbcf6e6": [
      2,
      40,
      42,
      41,
      43,
      46
    ],
    "75bedc26": [
      28
    ],
    "4c0847d2": [
      28
    ],
    "33db7382": [
      28
    ],
    "c3cb1460": [
      28
    ],
    "a9c926e8": [
      28
    ],
    "2fe66ec8": [
      2,
      40,
      42,
      41,
      43,
      46
    ],
    "638ccb9a": [
      2,
      40,
      42,
      41,
      43,
      46
    ],
    "cb315750": [
      2,
      40,
      42,
      41,
      43,
      46
    ],
    "42ac2cde": [
      2,
      40,
      42,
      41,
      43,
      46
    ],
    "15abd837": [
      2,
      40,
      42,
      41,
      43,
      46
    ],
    "3b05123e": [
      2,
      40,
      42,
      41,
      43,
      46
    ],
    "9f49281e": [
      2,
      40,
      42,
      41,
      43,
      46
    ],
    "1911953a": [
      28
    ],
    "45368e9e": [
      28
    ],
    "47fe25b4": [
      2,
      40,
      42,
      41,
      43,
      46
    ],
    "ac40a638": [
      2,
      40,
      42,
      41,
      43,
      46
    ],
    "7c39d681": [
      28
    ],
    "1d3fbaee": [
      18
    ],
    "74e22bea": [
      18
    ],
    "6a3a0a50": [
      18
    ],
    "4a2e06a3": [
      18
    ],
    "5fd55082": [
      18
    ],
    "54c35ffa": [
      18
    ],
    "5105241a": [
      18
    ],
    "0f648b7f": [
      18
    ],
    "e6df93ca": [
      18
    ],
    "d0ec17b6": [
      18
    ],
    "a10c2e06": [
      18
    ],
    "bfd3aed2": [
      18
    ],
    "7b9b33aa": [
      18
    ],
    "1dd1b0b4": [
      18
    ],
    "25c431d2": [
      18
    ],
    "6048d0e5": [
      18
    ],
    "4fd98b77": [
      18
    ],
    "463c085e": [
      18
    ],
    "15b072d6": [
      18
    ],
    "ed9759ac": [
      18
    ],
    "4a0ef4da": [
      18
    ],
    "63e21df1": [
      18
    ],
    "2ea07bd0": [
      18
    ],
    "ebb7ce9c": [
      18
    ],
    "23d21029": [
      18
    ],
    "75a4596e": [
      18
    ],
    "e00a3652": [
      18
    ],
    "43bacd37": [
      18
    ],
    "16d71a4e": [
      18
    ],
    "040042b8": [
      18
    ],
    "db6cb122": [
      18
    ],
    "280cf73b": [
      18
    ],
    "3ee9c29d": [
      18
    ],
    "6b60bca9": [
      18
    ],
    "123921a5": [
      18
    ],
    "3155d278": [
      18
    ],
    "a0003a82": [
      18
    ],
    "25fb7b8f": [
      18
    ],
    "05990bd6": [
      18
    ],
    "4b2c3152": [
      18
    ],
    "6c103f6e": [
      18
    ],
    "7f481bb4": [
      18
    ],
    "0118674a": [
      18
    ],
    "bd0af81c": [
      18
    ],
    "18359bde": [
      18
    ],
    "208a26f5": [
      18
    ],
    "28aaf55f": [
      18
    ],
    "6d78114c": [
      18
    ],
    "c9e2d3d0": [
      18
    ],
    "2b8834bb": [
      18
    ],
    "6eef0cfa": [
      18
    ],
    "ce550d88": [
      18
    ],
    "b29c8928": [
      18
    ],
    "53ca5e5f": [
      18
    ],
    "152b053b": [
      18
    ],
    "d26c835e": [
      18
    ],
    "84c4be74": [
      18
    ],
    "aa99c2b0": [
      18
    ],
    "684dc2e3": [
      2,
      40,
      42,
      41,
      43,
      46
    ],
    "3dad7f1e": [
      28
    ],
    "53d5dde6": [
      2,
      40,
      42,
      41,
      43,
      46
    ],
    "09182fb5": [
      28
    ],
    "0694fb32": [
      28
    ],
    "6b267fc0": [
      28
    ],
    "635da4e0": [
      28
    ],
    "688e042e": [
      28
    ],
    "5b91984f": [
      2,
      40,
      42,
      41,
      43,
      46
    ],
    "0c990255": [
      2,
      40,
      42,
      41,
      43,
      46
    ],
    "75201b3e": [
      2,
      40,
      42,
      41,
      43,
      46
    ],
    "d32cbc84": [
      2,
      40,
      42,
      41,
      43,
      46
    ],
    "c9f41e42": [
      2,
      40,
      42,
      41,
      43,
      46
    ],
    "32d22dd1": [
      2,
      40,
      42,
      41,
      43,
      46
    ],
    "1cf8ce60": [
      2,
      40,
      42,
      41,
      43,
      46
    ],
    "63ac4913": [
      28
    ],
    "77545b9c": [
      2,
      40,
      42,
      41,
      43,
      46
    ],
    "51691ad0": [
      28
    ],
    "9933996a": [
      2,
      40,
      42,
      41,
      43,
      46
    ],
    "ac56d3d0": [
      2,
      40,
      42,
      41,
      43,
      46
    ],
    "0549ec20": [
      2,
      40,
      42,
      41,
      43,
      46
    ],
    "9ca36abc": [
      2,
      40,
      42,
      41,
      43,
      46
    ],
    "5b3e2de9": [
      2,
      40,
      42,
      41,
      43,
      46
    ],
    "438926d2": [
      2,
      40,
      42,
      41,
      43,
      46
    ],
    "38dbf4b7": [
      2,
      40,
      42,
      41,
      43,
      46
    ],
    "54096e90": [
      2,
      40,
      42,
      41,
      43,
      46
    ],
    "0753a516": [
      2,
      40,
      42,
      41,
      43,
      46
    ],
    "1752675a": [
      2,
      40,
      42,
      41,
      43,
      46
    ],
    "2b93dabe": [
      2,
      40,
      42,
      41,
      43,
      46
    ],
    "16415bb0": [
      2,
      40,
      42,
      41,
      43,
      46
    ],
    "47f7fec0": [
      2,
      40,
      42,
      41,
      43,
      46
    ],
    "ee259928": [
      2,
      40,
      42,
      41,
      43,
      46
    ],
    "75f46fa2": [
      2,
      40,
      42,
      41,
      43,
      46
    ],
    "4bc003cb": [
      2,
      40,
      42,
      41,
      43,
      46
    ],
    "69d366b6": [
      2,
      40,
      42,
      41,
      43,
      46
    ],
    "2ad01c26": [
      2,
      40,
      42,
      41,
      43,
      46
    ],
    "5d7ea162": [
      2,
      40,
      42,
      41,
      43,
      46
    ],
    "bbfdc594": [
      28
    ],
    "e322ece6": [
      28
    ],
    "8641c7f6": [
      28
    ],
    "f5c97a42": [
      28
    ],
    "6d572a54": [
      2,
      40,
      42,
      41,
      43,
      46
    ],
    "1c225bb0": [
      28
    ],
    "2ac6fcae": [
      2,
      40,
      42,
      41,
      43,
      46
    ],
    "15a39d26": [
      28
    ],
    "6706b700": [
      2,
      40,
      42,
      41,
      43,
      46
    ],
    "695de001": [
      2,
      40,
      42,
      41,
      43,
      46
    ],
    "1246451f": [
      2,
      40,
      42,
      41,
      43,
      46
    ],
    "384320a4": [
      2,
      40,
      42,
      41,
      43,
      46
    ],
    "10242e9e": [
      28
    ],
    "fc812b6c": [
      28
    ],
    "08a8b702": [
      28
    ],
    "0c65d2f0": [
      28
    ],
    "965c8994": [
      28
    ],
    "1441e266": [
      28
    ],
    "143d56b0": [
      28
    ],
    "476cf275": [
      28
    ],
    "e84528aa": [
      28
    ],
    "61470c35": [
      28
    ],
    "7606e3c4": [
      28
    ],
    "365a7fe1": [
      2,
      40,
      42,
      41,
      43,
      46
    ],
    "d2e2424e": [
      2,
      40,
      42,
      41,
      43,
      46
    ],
    "1b3e1cba": [
      2,
      40,
      42,
      41,
      43,
      46
    ],
    "44ae43bf": [
      2,
      40,
      42,
      41,
      43,
      46
    ],
    "5886dfa1": [
      2,
      40,
      42,
      41,
      43,
      46
    ],
    "18d3cc7b": [
      2,
      40,
      42,
      41,
      43,
      46
    ],
    "014ed465": [
      2,
      40,
      42,
      41,
      43,
      46
    ],
    "6a163c2f": [
      28
    ],
    "58aebca1": [
      28
    ],
    "f203f098": [
      2,
      40,
      42,
      41,
      43,
      46
    ],
    "a0b6ef14": [
      2,
      40,
      42,
      41,
      43,
      46
    ],
    "67f8067a": [
      2,
      40,
      42,
      41,
      43,
      46
    ],
    "2dc82286": [
      2,
      40,
      42,
      41,
      43,
      46
    ],
    "2da87e67": [
      2,
      40,
      42,
      41,
      43,
      46
    ],
    "07080e8b": [
      2,
      40,
      42,
      41,
      43,
      46
    ],
    "bcedc2c8": [
      2,
      40,
      42,
      41,
      43,
      46
    ],
    "c5f54fac": [
      2,
      40,
      42,
      41,
      43,
      46
    ],
    "30d98541": [
      2,
      40,
      42,
      41,
      43,
      46
    ],
    "8b949802": [
      2,
      40,
      42,
      41,
      43,
      46
    ],
    "5016f772": [
      2,
      40,
      42,
      41,
      43,
      46
    ],
    "6df849b8": [
      2,
      40,
      42,
      41,
      43,
      46
    ],
    "65988a46": [
      2,
      40,
      42,
      41,
      43,
      46
    ],
    "f263eed2": [
      2,
      40,
      42,
      41,
      43,
      46
    ],
    "59ccb37c": [
      2,
      40,
      42,
      41,
      43,
      46
    ],
    "74f30f33": [
      2,
      40,
      42,
      41,
      43,
      46
    ],
    "df47a936": [
      2,
      40,
      42,
      41,
      43,
      46
    ],
    "3c3c04c9": [
      2,
      40,
      42,
      41,
      43,
      46
    ],
    "4b5e845c": [
      2,
      40,
      42,
      41,
      43,
      46
    ],
    "3bd80325": [
      2,
      40,
      42,
      41,
      43,
      46
    ],
    "3f2a39d5": [
      2,
      40,
      42,
      41,
      43,
      46
    ],
    "d211c4a4": [
      2,
      40,
      42,
      41,
      43,
      46
    ],
    "7f09cc2c": [
      2,
      40,
      42,
      41,
      43,
      46
    ],
    "3c2cf37a": [
      2,
      40,
      42,
      41,
      43,
      46
    ],
    "323f5596": [
      28
    ],
    "000fde3b": [
      28
    ],
    "708ec602": [
      2,
      40,
      42,
      41,
      43,
      46
    ],
    "b8127616": [
      28
    ],
    "ccaf5d60": [
      28
    ],
    "555c21bb": [
      2,
      40,
      42,
      41,
      43,
      46
    ],
    "1db4be82": [
      28
    ],
    "f1eef47e": [
      28
    ],
    "6c463349": [
      2,
      40,
      42,
      41,
      43,
      46
    ],
    "4523167f": [
      28
    ],
    "26d239ef": [
      28
    ],
    "0d6d576b": [
      28
    ],
    "548097dc": [
      28
    ],
    "4455db5a": [
      28
    ],
    "3b2f32d2": [
      28
    ],
    "d3d2381a": [
      28
    ],
    "2700f453": [
      28
    ],
    "00b5a0c8": [
      2,
      40,
      42,
      41,
      43,
      46
    ],
    "52c3dd44": [
      2,
      40,
      42,
      41,
      43,
      46
    ],
    "3bc68203": [
      2,
      40,
      42,
      41,
      43,
      46
    ],
    "209f9194": [
      2,
      40,
      42,
      41,
      43,
      46
    ],
    "664435e2": [
      2,
      40,
      42,
      41,
      43,
      46
    ],
    "5d5f69a6": [
      2,
      40,
      42,
      41,
      43,
      46
    ],
    "2dd81c02": [
      2,
      40,
      42,
      41,
      43,
      46
    ],
    "27e82f34": [
      2,
      40,
      42,
      41,
      43,
      46
    ],
    "0b4e31a7": [
      2,
      40,
      42,
      41,
      43,
      46
    ],
    "268bb912": [
      2,
      40,
      42,
      41,
      43,
      46
    ],
    "2bc78026": [
      28
    ],
    "52701b3e": [
      2,
      40,
      42,
      41,
      43,
      46
    ],
    "53e01b7f": [
      2,
      40,
      42,
      41,
      43,
      46
    ],
    "2f8f29de": [
      18
    ],
    "5a605d57": [
      2,
      40,
      42,
      41,
      43,
      46
    ],
    "2fbdc539": [
      2,
      40,
      42,
      41,
      43,
      46
    ],
    "4fb5a161": [
      2,
      40,
      42,
      41,
      43,
      46
    ],
    "2c243ee6": [
      18
    ],
    "3c2523c6": [
      2,
      40,
      42,
      41,
      43,
      46
    ],
    "6342e437": [
      28
    ],
    "0407c09e": [
      2,
      40,
      42,
      41,
      43,
      46
    ],
    "4140ceb2": [
      28
    ],
    "5d1fbea6": [
      28
    ],
    "19dc4c29": [
      28
    ],
    "dda093e8": [
      28
    ],
    "1194659c": [
      28
    ],
    "6a76b99d": [
      28
    ],
    "5bdf1941": [
      28
    ],
    "28ad35de": [
      28
    ],
    "8cf6edc0": [
      28
    ],
    "aa0222be": [
      28
    ],
    "218debce": [
      28
    ],
    "3cf2d174": [
      28
    ],
    "011392da": [
      28
    ],
    "6799dab6": [
      28
    ],
    "b521dc5e": [
      28
    ],
    "5f6997d2": [
      2,
      40,
      42,
      41,
      43,
      46
    ],
    "b3576dfa": [
      2,
      40,
      42,
      41,
      43,
      46
    ],
    "63a1f977": [
      2,
      40,
      42,
      41,
      43,
      46
    ],
    "7ae480f0": [
      2,
      40,
      42,
      41,
      43,
      46
    ],
    "231b9670": [
      2,
      40,
      42,
      41,
      43,
      46
    ],
    "570e8b7c": [
      2,
      40,
      42,
      41,
      43,
      46
    ],
    "4df27ef0": [
      2,
      40,
      42,
      41,
      43,
      46
    ],
    "75de8969": [
      2,
      40,
      42,
      41,
      43,
      46
    ],
    "07bd9ab6": [
      2,
      40,
      42,
      41,
      43,
      46
    ],
    "307b84d3": [
      2,
      40,
      42,
      41,
      43,
      46
    ],
    "045a3657": [
      2,
      40,
      42,
      41,
      43,
      46
    ],
    "0f2c56d2": [
      2,
      40,
      42,
      41,
      43,
      46
    ],
    "aed9d066": [
      2,
      40,
      42,
      41,
      43,
      46
    ],
    "2494fb22": [
      2,
      40,
      42,
      41,
      43,
      46
    ],
    "2a63a738": [
      2,
      40,
      42,
      41,
      43,
      46
    ],
    "46dd3cb7": [
      2,
      40,
      42,
      41,
      43,
      46
    ],
    "0f16fc92": [
      2,
      40,
      42,
      41,
      43,
      46
    ],
    "451ab5e9": [
      2,
      40,
      42,
      41,
      43,
      46
    ],
    "6e11cb01": [
      18
    ],
    "4a3e4300": [
      2,
      40,
      42,
      41,
      43,
      46
    ],
    "18c376e0": [
      28
    ],
    "25f04314": [
      28
    ],
    "0920678f": [
      28
    ],
    "0ad12740": [
      2,
      40,
      42,
      41,
      43,
      46
    ],
    "1487352e": [
      2,
      40,
      42,
      41,
      43,
      46
    ],
    "5b71489e": [
      18
    ],
    "fa58e0bc": [
      28
    ],
    "b4b834ec": [
      28
    ],
    "1ef83dae": [
      28
    ],
    "b57e2e06": [
      28
    ],
    "d99ee262": [
      2,
      40,
      42,
      41,
      43,
      46
    ],
    "515ae3ea": [
      2,
      40,
      42,
      41,
      43,
      46
    ],
    "67b09341": [
      2,
      40,
      42,
      41,
      43,
      46
    ],
    "bd747e70": [
      2,
      40,
      42,
      41,
      43,
      46
    ],
    "0d0f198c": [
      28
    ],
    "347865c9": [
      2,
      40,
      42,
      41,
      43,
      46
    ],
    "7f8f79cf": [
      2,
      40,
      42,
      41,
      43,
      46
    ],
    "38dd1fa0": [
      2,
      40,
      42,
      41,
      43,
      46
    ],
    "89ec88c6": [
      28
    ],
    "4e680ac7": [
      28
    ],
    "05a79c4c": [
      28
    ],
    "fb670556": [
      28
    ],
    "2ff3397e": [
      28
    ],
    "dbab5cf2": [
      28
    ],
    "55dc47eb": [
      28
    ],
    "4c7362d4": [
      28
    ],
    "98b2d53e": [
      28
    ],
    "8a65abdc": [
      28
    ],
    "748f180f": [
      28
    ],
    "1d8644fc": [
      28
    ],
    "4d41a4bd": [
      28
    ],
    "6171c2c0": [
      28
    ],
    "38859b56": [
      28
    ],
    "2a40deea": [
      28
    ],
    "176b94a5": [
      28
    ],
    "67c6f86a": [
      28
    ],
    "485451ea": [
      28
    ],
    "8a4fb00a": [
      18
    ],
    "5327f6f2": [
      18
    ],
    "300328f3": [
      28
    ],
    "8fa8d8aa": [
      28
    ],
    "39c09d15": [
      2,
      40,
      42,
      41,
      43,
      46
    ],
    "70467c86": [
      2,
      40,
      42,
      41,
      43,
      46
    ],
    "581f4b06": [
      2,
      40,
      42,
      41,
      43,
      46
    ],
    "7f05890e": [
      2,
      40,
      42,
      41,
      43,
      46
    ],
    "353fff07": [
      2,
      40,
      42,
      41,
      43,
      46
    ],
    "b53ca592": [
      2,
      40,
      42,
      41,
      43,
      46
    ],
    "5ffc27c0": [
      2,
      40,
      42,
      41,
      43,
      46
    ],
    "4d5acd26": [
      2,
      40,
      42,
      41,
      43,
      46
    ],
    "66875dad": [
      2,
      40,
      42,
      41,
      43,
      46
    ],
    "c2c2fcc6": [
      18
    ],
    "d23058b2": [
      18
    ],
    "1964a43a": [
      2,
      40,
      42,
      41,
      43,
      46
    ],
    "1348ba90": [
      2,
      40,
      42,
      41,
      43,
      46
    ],
    "b228d302": [
      2,
      40,
      42,
      41,
      43,
      46
    ],
    "903b8e2c": [
      2,
      40,
      42,
      41,
      43,
      46
    ],
    "7d98eea9": [
      2,
      40,
      42,
      41,
      43,
      46
    ],
    "8609a7bc": [
      2,
      40,
      42,
      41,
      43,
      46
    ],
    "908790c2": [
      2,
      40,
      42,
      41,
      43,
      46
    ],
    "1f3b2e9e": [
      28
    ],
    "2289a796": [
      2,
      40,
      42,
      41,
      43,
      46
    ],
    "43961a88": [
      28
    ],
    "08d35d95": [
      2,
      40,
      42,
      41,
      43,
      46
    ],
    "5aaefdb7": [
      2,
      40,
      42,
      41,
      43,
      46
    ],
    "0bd2efbf": [
      18
    ],
    "1006c464": [
      28
    ],
    "49585b9a": [
      28
    ],
    "cda37b3c": [
      28
    ],
    "3df63176": [
      28
    ],
    "f6cb9d8e": [
      28
    ],
    "2f79d31c": [
      28
    ],
    "38fc70cf": [
      2,
      40,
      42,
      41,
      43,
      46
    ],
    "00994659": [
      28
    ],
    "c9e75d3c": [
      9
    ],
    "a2dfff7c": [
      28
    ],
    "3b7ec491": [
      28
    ],
    "2d2b400c": [
      18
    ],
    "96ba2aba": [
      28
    ],
    "38e8b55d": [
      28
    ],
    "f5444c90": [
      28
    ],
    "d83fcbae": [
      2,
      40,
      42,
      41,
      43,
      46
    ],
    "4cfc058a": [
      2,
      40,
      42,
      41,
      43,
      46
    ],
    "9a1a185e": [
      2,
      40,
      42,
      41,
      43,
      46
    ],
    "b80e39c0": [
      2,
      40,
      42,
      41,
      43,
      46
    ],
    "6d670962": [
      2,
      40,
      42,
      41,
      43,
      46
    ],
    "b001199c": [
      2,
      40,
      42,
      41,
      43,
      46
    ],
    "0ea38c3e": [
      18
    ],
    "0d4f2fb0": [
      18
    ],
    "d6d5f374": [
      28
    ],
    "73ccd22b": [
      28
    ],
    "04080f1a": [
      28
    ],
    "be7ed50a": [
      28
    ],
    "452bb392": [
      28
    ],
    "15964aa9": [
      28
    ],
    "b4456448": [
      28
    ],
    "5046ed44": [
      28
    ],
    "a377f11e": [
      28
    ],
    "d233cfce": [
      28
    ],
    "c61db8ca": [
      28
    ],
    "6ae8ef06": [
      28
    ],
    "04a6cb08": [
      28
    ],
    "2c0c4173": [
      28
    ],
    "092308c5": [
      28
    ],
    "da3e457a": [
      28
    ],
    "ee458e3c": [
      18
    ],
    "0bdc459f": [
      18
    ],
    "4d5ae2cd": [
      18
    ],
    "fa25c90e": [
      28
    ],
    "01afe695": [
      28
    ],
    "1d7600c0": [
      28
    ],
    "3d5ba706": [
      28
    ],
    "a056af9a": [
      28
    ],
    "6f68a6a6": [
      28
    ],
    "4ccf2c44": [
      28
    ],
    "fddb4316": [
      18
    ],
    "6649e566": [
      18
    ],
    "121af6fe": [
      18
    ],
    "734add59": [
      18
    ],
    "7abb22a8": [
      2,
      40,
      42,
      41,
      43,
      46
    ],
    "1c78fd0c": [
      2,
      40,
      42,
      41,
      43,
      46
    ],
    "515a9d94": [
      2,
      40,
      42,
      41,
      43,
      46
    ],
    "4c4e8f89": [
      2,
      40,
      42,
      41,
      43,
      46
    ],
    "66a00a19": [
      2,
      40,
      42,
      41,
      43,
      46
    ],
    "46ff4c72": [
      2,
      40,
      42,
      41,
      43,
      46
    ],
    "724cdf36": [
      2,
      40,
      42,
      41,
      43,
      46
    ],
    "5cc20b2a": [
      2,
      40,
      42,
      41,
      43,
      46
    ],
    "6c87e352": [
      28
    ],
    "54ef856e": [
      2,
      40,
      42,
      41,
      43,
      46
    ],
    "c3abbf08": [
      28
    ],
    "27d5bd7c": [
      28
    ],
    "47cd9ba9": [
      2,
      40,
      42,
      41,
      43,
      46
    ],
    "04958c0c": [
      2,
      40,
      42,
      41,
      43,
      46
    ],
    "b6a34bc6": [
      28
    ],
    "359dfa93": [
      2,
      40,
      42,
      41,
      43,
      46
    ],
    "f47cb73c": [
      2,
      40,
      42,
      41,
      43,
      46
    ],
    "a8ccbb32": [
      28
    ],
    "0fe3b71c": [
      28
    ],
    "403c76ae": [
      2,
      40,
      42,
      41,
      43,
      46
    ],
    "8b49da8c": [
      2,
      40,
      42,
      41,
      43,
      46
    ],
    "14f7af2e": [
      2,
      40,
      42,
      41,
      43,
      46
    ],
    "7f5cd18c": [
      2,
      40,
      42,
      41,
      43,
      46
    ],
    "4069761f": [
      2,
      40,
      42,
      41,
      43,
      46
    ],
    "0b36e4f0": [
      2,
      40,
      42,
      41,
      43,
      46
    ],
    "5fd9cb2e": [
      2,
      40,
      42,
      41,
      43,
      46
    ],
    "1d4018fa": [
      2,
      40,
      42,
      41,
      43,
      46
    ],
    "f2cb050c": [
      2,
      40,
      42,
      41,
      43,
      46
    ],
    "e4b2ad6e": [
      2,
      40,
      42,
      41,
      43,
      46
    ],
    "d3e55532": [
      2,
      40,
      42,
      41,
      43,
      46
    ],
    "22ffae14": [
      2,
      40,
      42,
      41,
      43,
      46
    ],
    "3551754c": [
      2,
      40,
      42,
      41,
      43,
      46
    ],
    "298dd8c6": [
      2,
      40,
      42,
      41,
      43,
      46
    ],
    "0ab81b26": [
      2,
      40,
      42,
      41,
      43,
      46
    ],
    "05079ebc": [
      2,
      40,
      42,
      41,
      43,
      46
    ],
    "305b3f89": [
      2,
      40,
      42,
      41,
      43,
      46
    ],
    "726d1d1a": [
      2,
      40,
      42,
      41,
      43,
      46
    ],
    "3b5e2911": [
      2,
      40,
      42,
      41,
      43,
      46
    ],
    "5bb074e2": [
      2,
      40,
      42,
      41,
      43,
      46
    ],
    "3bad02c9": [
      2,
      40,
      42,
      41,
      43,
      46
    ],
    "162650da": [
      2,
      40,
      42,
      41,
      43,
      46
    ],
    "55fd7869": [
      2,
      40,
      42,
      41,
      43,
      46
    ],
    "ff6b310c": [
      2,
      40,
      42,
      41,
      43,
      46
    ],
    "484da19a": [
      2,
      40,
      42,
      41,
      43,
      46
    ],
    "3e2c26f8": [
      2,
      40,
      42,
      41,
      43,
      46
    ],
    "80cbf66e": [
      2,
      40,
      42,
      41,
      43,
      46
    ],
    "2c32184c": [
      2,
      40,
      42,
      41,
      43,
      46
    ],
    "6effde03": [
      2,
      40,
      42,
      41,
      43,
      46
    ],
    "e15bac58": [
      2,
      40,
      42,
      41,
      43,
      46
    ],
    "4b572751": [
      2,
      40,
      42,
      41,
      43,
      46
    ],
    "6cb53522": [
      2,
      40,
      42,
      41,
      43,
      46
    ],
    "b7ed34ae": [
      2,
      40,
      42,
      41,
      43,
      46
    ],
    "6353568c": [
      2,
      40,
      42,
      41,
      43,
      46
    ],
    "22ecb9d7": [
      2,
      40,
      42,
      41,
      43,
      46
    ],
    "03c9dfa0": [
      2,
      40,
      42,
      41,
      43,
      46
    ],
    "460e15e9": [
      2,
      40,
      42,
      41,
      43,
      46
    ],
    "10db84ba": [
      2,
      40,
      42,
      41,
      43,
      46
    ],
    "000cb05f": [
      2,
      40,
      42,
      41,
      43,
      46
    ],
    "6a4bc1a0": [
      2,
      40,
      42,
      41,
      43,
      46
    ],
    "53df337f": [
      2,
      40,
      42,
      41,
      43,
      46
    ],
    "58eff0d0": [
      2,
      40,
      42,
      41,
      43,
      46
    ],
    "b358cb8a": [
      2,
      40,
      42,
      41,
      43,
      46
    ],
    "5c3b388c": [
      2,
      40,
      42,
      41,
      43,
      46
    ],
    "31f78b0f": [
      2,
      40,
      42,
      41,
      43,
      46
    ],
    "7e2dd730": [
      2,
      40,
      42,
      41,
      43,
      46
    ],
    "3bd43c6b": [
      2,
      40,
      42,
      41,
      43,
      46
    ],
    "6ef32485": [
      2,
      40,
      42,
      41,
      43,
      46
    ],
    "a7dbb9be": [
      2,
      40,
      42,
      41,
      43,
      46
    ],
    "373a2b7b": [
      2,
      40,
      42,
      41,
      43,
      46
    ],
    "6ec1dd9e": [
      2,
      40,
      42,
      41,
      43,
      46
    ],
    "faf10430": [
      2,
      40,
      42,
      41,
      43,
      46
    ],
    "b2b7418e": [
      2,
      40,
      42,
      41,
      43,
      46
    ],
    "6f7c3478": [
      2,
      40,
      42,
      41,
      43,
      46
    ],
    "c473683e": [
      2,
      40,
      42,
      41,
      43,
      46
    ],
    "da4aef78": [
      2,
      40,
      42,
      41,
      43,
      46
    ],
    "fbc1668a": [
      2,
      40,
      42,
      41,
      43,
      46
    ],
    "64570b9d": [
      2,
      40,
      42,
      41,
      43,
      46
    ],
    "ee324560": [
      2,
      40,
      42,
      41,
      43,
      46
    ],
    "eb3a38e8": [
      2,
      40,
      42,
      41,
      43,
      46
    ],
    "c53df678": [
      2,
      40,
      42,
      41,
      43,
      46
    ],
    "6fae6966": [
      2,
      40,
      42,
      41,
      43,
      46
    ],
    "5f0976c0": [
      2,
      40,
      42,
      41,
      43,
      46
    ],
    "390d3450": [
      2,
      40,
      42,
      41,
      43,
      46
    ],
    "fc9aceb6": [
      2,
      40,
      42,
      41,
      43,
      46
    ],
    "4595d12e": [
      2,
      40,
      42,
      41,
      43,
      46
    ],
    "e954a570": [
      2,
      40,
      42,
      41,
      43,
      46
    ],
    "e65c98f8": [
      2,
      40,
      42,
      41,
      43,
      46
    ],
    "c0605688": [
      2,
      40,
      42,
      41,
      43,
      46
    ],
    "054aba2d": [
      2,
      40,
      42,
      41,
      43,
      46
    ],
    "e47ff54e": [
      2,
      40,
      42,
      41,
      43,
      46
    ],
    "7a3c6733": [
      2,
      40,
      42,
      41,
      43,
      46
    ],
    "03e189c6": [
      2,
      40,
      42,
      41,
      43,
      46
    ],
    "0216aa7a": [
      2,
      40,
      42,
      41,
      43,
      46
    ],
    "721b6d87": [
      2,
      40,
      42,
      41,
      43,
      46
    ],
    "2ac0e45f": [
      2,
      40,
      42,
      41,
      43,
      46
    ],
    "9d405ef6": [
      2,
      40,
      42,
      41,
      43,
      46
    ],
    "0701c798": [
      2,
      40,
      42,
      41,
      43,
      46
    ],
    "8486354e": [
      2,
      40,
      42,
      41,
      43,
      46
    ],
    "8c4c0076": [
      2,
      40,
      42,
      41,
      43,
      46
    ],
    "6e560ff4": [
      2,
      40,
      42,
      41,
      43,
      46
    ],
    "260060f0": [
      2,
      40,
      42,
      41,
      43,
      46
    ],
    "00ce1a37": [
      2,
      40,
      42,
      41,
      43,
      46
    ],
    "1d154509": [
      2,
      40,
      42,
      41,
      43,
      46
    ],
    "b607e264": [
      2,
      40,
      42,
      41,
      43,
      46
    ],
    "57ad46b1": [
      2,
      40,
      42,
      41,
      43,
      46
    ],
    "d1f37f08": [
      2,
      40,
      42,
      41,
      43,
      46
    ],
    "304dde15": [
      2,
      40,
      42,
      41,
      43,
      46
    ],
    "01f6f8dc": [
      2,
      40,
      42,
      41,
      43,
      46
    ],
    "c6eca2ec": [
      2,
      40,
      42,
      41,
      43,
      46
    ],
    "46b0d3ac": [
      2,
      40,
      42,
      41,
      43,
      46
    ],
    "1a2818a4": [
      2,
      40,
      42,
      41,
      43,
      46
    ],
    "e7e8cfa4": [
      2,
      40,
      42,
      41,
      43,
      46
    ],
    "253b873a": [
      2,
      40,
      42,
      41,
      43,
      46
    ],
    "2d9be520": [
      2,
      40,
      42,
      41,
      43,
      46
    ],
    "3077c528": [
      2,
      40,
      42,
      41,
      43,
      46
    ],
    "cbad2e3a": [
      18
    ],
    "f1ece9ea": [
      18
    ],
    "00575b00": [
      28
    ],
    "541c108c": [
      2,
      40,
      42,
      41,
      43,
      46
    ],
    "be1ac66e": [
      2,
      40,
      42,
      41,
      43,
      46
    ],
    "23c0c94c": [
      2,
      40,
      42,
      41,
      43,
      46
    ],
    "24c9cfee": [
      2,
      40,
      42,
      41,
      43,
      46
    ],
    "3ac8169a": [
      2,
      40,
      42,
      41,
      43,
      46
    ],
    "3683a214": [
      2,
      40,
      42,
      41,
      43,
      46
    ],
    "bf451792": [
      2,
      40,
      42,
      41,
      43,
      46
    ],
    "05085088": [
      2,
      40,
      42,
      41,
      43,
      46
    ],
    "39aad149": [
      2,
      40,
      42,
      41,
      43,
      46
    ],
    "14241f5a": [
      2,
      40,
      42,
      41,
      43,
      46
    ],
    "e255b7be": [
      18
    ],
    "27462af9": [
      18
    ],
    "04281237": [
      2,
      40,
      42,
      41,
      43,
      46
    ],
    "8be09ef0": [
      2,
      40,
      42,
      41,
      43,
      46
    ],
    "01945e69": [
      2,
      40,
      42,
      41,
      43,
      46
    ],
    "47e4a70c": [
      2,
      40,
      42,
      41,
      43,
      46
    ],
    "b76127e8": [
      2,
      40,
      42,
      41,
      43,
      46
    ],
    "32aef0b6": [
      2,
      40,
      42,
      41,
      43,
      46
    ],
    "c6dfb414": [
      2,
      40,
      42,
      41,
      43,
      46
    ],
    "663b0dc2": [
      18
    ],
    "0780dea4": [
      18
    ],
    "230e18d6": [
      2,
      40,
      42,
      41,
      43,
      46
    ],
    "d4126364": [
      2,
      40,
      42,
      41,
      43,
      46
    ],
    "7bba205e": [
      2,
      40,
      42,
      41,
      43,
      46
    ],
    "8eaae3f6": [
      2,
      40,
      42,
      41,
      43,
      46
    ],
    "38fe9830": [
      2,
      40,
      42,
      41,
      43,
      46
    ],
    "36068bb8": [
      2,
      40,
      42,
      41,
      43,
      46
    ],
    "100a4948": [
      2,
      40,
      42,
      41,
      43,
      46
    ],
    "04dd75f3": [
      2,
      40,
      42,
      41,
      43,
      46
    ],
    "1a7831f6": [
      2,
      40,
      42,
      41,
      43,
      46
    ],
    "b5eeb552": [
      2,
      40,
      42,
      41,
      43,
      46
    ],
    "9e51c684": [
      2,
      40,
      42,
      41,
      43,
      46
    ],
    "2287936b": [
      2,
      40,
      42,
      41,
      43,
      46
    ],
    "67c7839e": [
      2,
      40,
      42,
      41,
      43,
      46
    ],
    "183b9b47": [
      2,
      40,
      42,
      41,
      43,
      46
    ],
    "3cd6c3bb": [
      2,
      40,
      42,
      41,
      43,
      46
    ],
    "523d6098": [
      2,
      40,
      42,
      41,
      43,
      46
    ],
    "3f66518c": [
      2,
      40,
      42,
      41,
      43,
      46
    ],
    "6958c0d4": [
      2,
      40,
      42,
      41,
      43,
      46
    ],
    "22c7d337": [
      2,
      40,
      42,
      41,
      43,
      46
    ],
    "83421f34": [
      2,
      40,
      42,
      41,
      43,
      46
    ],
    "e33040f6": [
      2,
      40,
      42,
      41,
      43,
      46
    ],
    "10552ed1": [
      2,
      40,
      42,
      41,
      43,
      46
    ],
    "e0283732": [
      2,
      40,
      42,
      41,
      43,
      46
    ],
    "eb3bb42c": [
      2,
      40,
      42,
      41,
      43,
      46
    ],
    "b404f258": [
      2,
      40,
      42,
      41,
      43,
      46
    ],
    "10ce1263": [
      2,
      40,
      42,
      41,
      43,
      46
    ],
    "053592e0": [
      2,
      40,
      42,
      41,
      43,
      46
    ],
    "bbbe1668": [
      2,
      40,
      42,
      41,
      43,
      46
    ],
    "6d6e2bda": [
      2,
      40,
      42,
      41,
      43,
      46
    ],
    "f941429c": [
      2,
      40,
      42,
      41,
      43,
      46
    ],
    "aed797ea": [
      2,
      40,
      42,
      41,
      43,
      46
    ],
    "8cafbcd4": [
      2,
      40,
      42,
      41,
      43,
      46
    ],
    "fef4b332": [
      2,
      40,
      42,
      41,
      43,
      46
    ],
    "1e4d52dd": [
      2,
      40,
      42,
      41,
      43,
      46
    ],
    "6185ceb6": [
      2,
      40,
      42,
      41,
      43,
      46
    ],
    "080ef6d8": [
      2,
      40,
      42,
      41,
      43,
      46
    ],
    "386d4bdd": [
      2,
      40,
      42,
      41,
      43,
      46
    ],
    "7a7f707e": [
      2,
      40,
      42,
      41,
      43,
      46
    ],
    "7057f556": [
      2,
      40,
      42,
      41,
      43,
      46
    ],
    "d8834cac": [
      2,
      40,
      42,
      41,
      43,
      46
    ],
    "effdbaca": [
      2,
      40,
      42,
      41,
      43,
      46
    ],
    "f2d9ebb8": [
      2,
      40,
      42,
      41,
      43,
      46
    ],
    "0f085550": [
      2,
      40,
      42,
      41,
      43,
      46
    ],
    "7fec6444": [
      2,
      40,
      42,
      41,
      43,
      46
    ],
    "6adaa26d": [
      2,
      40,
      42,
      41,
      43,
      46
    ],
    "e92820c0": [
      2,
      40,
      42,
      41,
      43,
      46
    ],
    "29dff2c3": [
      2,
      40,
      42,
      41,
      43,
      46
    ],
    "1a54a5a8": [
      2,
      40,
      42,
      41,
      43,
      46
    ],
    "40a9a897": [
      2,
      40,
      42,
      41,
      43,
      46
    ],
    "bba3cc18": [
      18
    ],
    "2f6abcfc": [
      18
    ],
    "3c6a75cc": [
      18
    ],
    "3d4cfae8": [
      18
    ],
    "13028aec": [
      18
    ],
    "c1447534": [
      18
    ],
    "ee473692": [
      18
    ],
    "04cb3c34": [
      18
    ],
    "a5ee5576": [
      18
    ],
    "0c980632": [
      2,
      40,
      42,
      41,
      43,
      46
    ],
    "52709f34": [
      2,
      40,
      42,
      41,
      43,
      46
    ],
    "3fc653a8": [
      2,
      40,
      42,
      41,
      43,
      46
    ],
    "2f52ae80": [
      2,
      40,
      42,
      41,
      43,
      46
    ],
    "2b1d8bdc": [
      2,
      40,
      42,
      41,
      43,
      46
    ],
    "1e3e2ad2": [
      2,
      40,
      42,
      41,
      43,
      46
    ],
    "166a9ddf": [
      2,
      40,
      42,
      41,
      43,
      46
    ],
    "9fcd9ee4": [
      2,
      40,
      42,
      41,
      43,
      46
    ],
    "58c1ad50": [
      2,
      40,
      42,
      41,
      43,
      46
    ],
    "6206a992": [
      2,
      40,
      42,
      41,
      43,
      46
    ],
    "0b18f697": [
      2,
      40,
      42,
      41,
      43,
      46
    ],
    "7fedd63f": [
      2,
      40,
      42,
      41,
      43,
      46
    ],
    "08526a7f": [
      2,
      40,
      42,
      41,
      43,
      46
    ],
    "8df2cad2": [
      2,
      40,
      42,
      41,
      43,
      46
    ],
    "14ddbbd2": [
      2,
      40,
      42,
      41,
      43,
      46
    ],
    "cc60f124": [
      2,
      40,
      42,
      41,
      43,
      46
    ],
    "6ceb1efe": [
      2,
      40,
      42,
      41,
      43,
      46
    ],
    "03b7f153": [
      2,
      40,
      42,
      41,
      43,
      46
    ],
    "465534d7": [
      2,
      40,
      42,
      41,
      43,
      46
    ],
    "bf803be6": [
      2,
      40,
      42,
      41,
      43,
      46
    ],
    "609b9401": [
      2,
      40,
      42,
      41,
      43,
      46
    ],
    "020fe8ec": [
      2,
      40,
      42,
      41,
      43,
      46
    ],
    "e875b564": [
      2,
      40,
      42,
      41,
      43,
      46
    ],
    "2f12b169": [
      2,
      40,
      42,
      41,
      43,
      46
    ],
    "01c848ad": [
      2,
      40,
      42,
      41,
      43,
      46
    ],
    "365cf865": [
      2,
      40,
      42,
      41,
      43,
      46
    ],
    "0b661a34": [
      2,
      40,
      42,
      41,
      43,
      46
    ],
    "10f80dda": [
      2,
      40,
      42,
      41,
      43,
      46
    ],
    "51ab686c": [
      2,
      40,
      42,
      41,
      43,
      46
    ],
    "6432e422": [
      2,
      40,
      42,
      41,
      43,
      46
    ],
    "3eeefa9e": [
      34
    ],
    "7e80a374": [
      34
    ],
    "148e175e": [
      9
    ],
    "03e01c5a": [
      9
    ],
    "d66551e2": [
      9
    ],
    "5efee86e": [
      9
    ],
    "e05cead2": [
      9
    ],
    "038ae34d": [
      34
    ],
    "b15aa096": [
      34
    ],
    "71e671c9": [
      34
    ],
    "3805d28a": [
      34
    ],
    "371ffcae": [
      9
    ],
    "baa99d44": [
      34
    ],
    "236218ca": [
      27
    ],
    "2f05131c": [
      35
    ],
    "397b8100": [
      11
    ],
    "0b63402a": [
      27
    ],
    "284bced4": [
      27
    ],
    "7cda9cb1": [
      9
    ],
    "1c0d137a": [
      34
    ],
    "7939cc38": [
      34
    ],
    "cf3b0bdc": [
      34
    ],
    "15ced80b": [
      34
    ],
    "59a6afa6": [
      34
    ],
    "d3df1f52": [
      27
    ],
    "1b967176": [
      27
    ],
    "9c23586a": [
      9
    ],
    "695cdbc8": [
      9
    ],
    "51c60816": [
      14
    ],
    "1815b640": [
      34
    ],
    "52d6841e": [
      34
    ],
    "914aca44": [
      34
    ],
    "59a88f1a": [
      34
    ],
    "63811ec4": [
      34
    ],
    "03cf6c04": [
      34
    ],
    "55a339cc": [
      34
    ],
    "0d246fbe": [
      34
    ],
    "51e9f678": [
      34
    ],
    "68be701e": [
      34
    ],
    "2cfb4e5e": [
      34
    ],
    "77de5834": [
      34
    ],
    "38c7b39e": [
      34
    ],
    "4ec4ba28": [
      34
    ],
    "32f3aac4": [
      34
    ],
    "3b95273e": [
      34
    ],
    "675a2b9e": [
      34
    ],
    "7ea67b1e": [
      34
    ],
    "78a39c4c": [
      34
    ],
    "e2aa45c4": [
      34
    ],
    "2d3537fe": [
      34
    ],
    "258cfede": [
      34
    ],
    "6ce538c6": [
      34
    ],
    "2e06f684": [
      34
    ],
    "efcbe984": [
      34
    ],
    "1a0ee84c": [
      34
    ],
    "7692e623": [
      34
    ],
    "724912ea": [
      34
    ],
    "3c7b7693": [
      34
    ],
    "4f2ff861": [
      9
    ],
    "8454651e": [
      9
    ],
    "1e8f39f4": [
      34
    ],
    "6fed44ea": [
      27
    ],
    "7df0fbdc": [
      27
    ],
    "5fe5aa9d": [
      9
    ],
    "2ab3196e": [
      9
    ],
    "5c74c323": [
      9
    ],
    "125c6174": [
      9
    ],
    "c5e7617a": [
      9
    ],
    "be3a0758": [
      9
    ],
    "3928ba29": [
      9
    ],
    "7b3a97ba": [
      9
    ],
    "0fd552c3": [
      9
    ],
    "4aba7cd8": [
      9
    ],
    "1764be89": [
      35
    ],
    "59769c1a": [
      35
    ],
    "04dc541e": [
      35
    ],
    "08b3012f": [
      35
    ],
    "8d710388": [
      35
    ],
    "22272b0d": [
      35
    ],
    "72e4de51": [
      35
    ],
    "77f59ba2": [
      35
    ],
    "1ae4647f": [
      14
    ],
    "5e67fa60": [
      14
    ],
    "1a240cfd": [
      14
    ],
    "658c0b68": [
      14
    ],
    "e2b22dd4": [
      14
    ],
    "3e4ea5a7": [
      14
    ],
    "654c9a6b": [
      14
    ],
    "ec91c486": [
      14
    ],
    "2a2b6d47": [
      14
    ],
    "457d4ad4": [
      14
    ],
    "2e146e3f": [
      14
    ],
    "3dab48e4": [
      14
    ],
    "97f1c034": [
      12
    ],
    "28b793f5": [
      12
    ],
    "f89a4fda": [
      12
    ],
    "ee78d538": [
      12
    ],
    "1009352e": [
      34
    ],
    "5b16990c": [
      34
    ],
    "b22735d0": [
      32,
      27,
      39,
      44,
      45
    ],
    "b20b06ce": [
      32,
      27,
      39,
      44,
      45
    ],
    "b07eced8": [
      39
    ],
    "0a752ff5": [
      39
    ],
    "d7842ad2": [
      39
    ],
    "d9fdee8e": [
      27
    ],
    "3c35d94e": [
      12
    ],
    "8cb7fb7e": [
      12
    ],
    "4ab87152": [
      34
    ],
    "06a5f311": [
      14
    ],
    "5d7823e5": [
      14
    ],
    "4139c17d": [
      14
    ],
    "dea0cafa": [
      14
    ],
    "7133eda7": [
      14
    ],
    "06853936": [
      14
    ],
    "1f9e197c": [
      14
    ],
    "0da73db0": [
      14
    ],
    "573ef1da": [
      14
    ],
    "be5e86f8": [
      14
    ],
    "5a6df553": [
      14
    ],
    "29acd7f8": [
      14
    ],
    "5a534185": [
      14
    ],
    "671cc00a": [
      14
    ],
    "72f869a8": [
      14
    ],
    "ca76e8aa": [
      14
    ],
    "4941c9a4": [
      14
    ],
    "3df00c1f": [
      14
    ],
    "e9cd86a6": [
      14
    ],
    "d605161e": [
      17,
      27,
      9,
      35,
      14
    ],
    "42fa206c": [
      17,
      27,
      9,
      35,
      14
    ],
    "03621c1f": [
      17,
      27,
      9,
      35,
      14
    ],
    "388bb178": [
      17,
      27,
      9,
      35,
      14
    ],
    "6347486d": [
      17,
      27,
      9,
      35,
      14
    ],
    "ad32fffc": [
      17,
      27,
      9,
      35,
      14
    ],
    "0b36f108": [
      17,
      27,
      9,
      35,
      14
    ],
    "147f7e24": [
      17,
      27,
      9,
      35,
      14
    ],
    "4f129802": [
      17,
      27,
      9,
      35,
      14
    ],
    "27cce3bc": [
      17,
      27,
      9,
      35,
      14
    ],
    "41d8ae4e": [
      17,
      27,
      9,
      35,
      14
    ],
    "5ec364fb": [
      17,
      27,
      9,
      35,
      14
    ],
    "7e1ef122": [
      17,
      27,
      9,
      35,
      14
    ],
    "19eab416": [
      17,
      27,
      9,
      35,
      14
    ],
    "796a41f0": [
      17,
      27,
      9,
      35,
      14
    ],
    "97f9b212": [
      35
    ],
    "c71105ac": [
      35
    ],
    "357e7fff": [
      35
    ],
    "6708697f": [
      35
    ],
    "719e3ee8": [
      35
    ],
    "820ce430": [
      35
    ],
    "21e18c17": [
      35
    ],
    "1977257d": [
      35
    ],
    "130f6b6f": [
      35
    ],
    "c374c680": [
      35
    ],
    "21cd1d9e": [
      35
    ],
    "94e84896": [
      35
    ],
    "a9e7c768": [
      35
    ],
    "358c4099": [
      35
    ],
    "1360e57c": [
      7,
      27,
      9,
      35
    ],
    "5f3d7cae": [
      7,
      27,
      9,
      35
    ],
    "0900ec98": [
      7,
      27,
      9,
      35
    ],
    "64a882a3": [
      7,
      27,
      9,
      35
    ],
    "126a4afc": [
      7,
      27,
      9,
      35
    ],
    "db70d7bc": [
      7,
      27,
      9,
      35
    ],
    "6ee7ceec": [
      7,
      27,
      9,
      35
    ],
    "846b8f64": [
      7,
      27,
      9,
      35
    ],
    "50309af8": [
      7,
      27,
      9,
      35
    ],
    "000cc41c": [
      7,
      27,
      9,
      35
    ],
    "c49ace0e": [
      19,
      27,
      9,
      35
    ],
    "e47e3c50": [
      19,
      27,
      9,
      35
    ],
    "78ee2bb5": [
      19,
      27,
      9,
      35
    ],
    "6e9d2d1e": [
      19,
      27,
      9,
      35
    ],
    "9089a8b2": [
      19,
      27,
      9,
      35
    ],
    "5f15e66e": [
      19,
      27,
      9,
      35
    ],
    "d14d9f0a": [
      19,
      27,
      9,
      35
    ],
    "2d4d4e42": [
      19,
      27,
      9,
      35
    ],
    "f1bfcc16": [
      19,
      27,
      9,
      35
    ],
    "0225f090": [
      19,
      27,
      9,
      35
    ],
    "07ca128f": [
      6,
      27,
      9,
      35
    ],
    "5d530a22": [
      6,
      27,
      9,
      35
    ],
    "aea6897e": [
      6,
      27,
      9,
      35
    ],
    "0c039869": [
      6,
      27,
      9,
      35
    ],
    "437fb98f": [
      6,
      27,
      9,
      35
    ],
    "07deaa7c": [
      6,
      27,
      9,
      35
    ],
    "ffae3250": [
      6,
      27,
      9,
      35
    ],
    "7ec1cc2e": [
      6,
      27,
      9,
      35
    ],
    "cc494c5c": [
      6,
      27,
      9,
      35
    ],
    "7ffb12fc": [
      6,
      27,
      9,
      35
    ],
    "5c696f91": [
      37,
      27
    ],
    "29619b85": [
      37,
      27
    ],
    "0c5ece1d": [
      37,
      27
    ],
    "d04d9a6a": [
      37,
      27
    ],
    "6f3df20f": [
      37,
      27
    ],
    "4d1a13f0": [
      37,
      27
    ],
    "574c7b04": [
      37,
      27
    ],
    "24576e74": [
      37,
      27
    ],
    "0e079a6c": [
      37,
      27
    ],
    "ead6b390": [
      37,
      27
    ],
    "5d6ca340": [
      32,
      27,
      39,
      44,
      45
    ],
    "222e513a": [
      32,
      27,
      39,
      44,
      45
    ],
    "6352e2a4": [
      32,
      27,
      39,
      44,
      45
    ],
    "5e465500": [
      32,
      27,
      39,
      44,
      45
    ],
    "b7832cc0": [
      32,
      27,
      39,
      44,
      45
    ],
    "55eb5599": [
      32,
      27,
      39,
      44,
      45
    ],
    "18a6a7b6": [
      32,
      27,
      39,
      44,
      45
    ],
    "7d8f7256": [
      32,
      27,
      39,
      44,
      45
    ],
    "438f10eb": [
      32,
      27,
      39,
      44,
      45
    ],
    "22c89b47": [
      32,
      27,
      39,
      44,
      45
    ],
    "435deb10": [
      20
    ],
    "4b46522c": [
      20
    ],
    "f97d2a84": [
      20
    ],
    "73fa55f2": [
      20
    ],
    "950227a0": [
      20
    ],
    "1b9fac6c": [
      20
    ],
    "cb99957a": [
      20
    ],
    "fe33f986": [
      20
    ],
    "5f5d8180": [
      16
    ],
    "2887116b": [
      16
    ],
    "bc914a64": [
      16
    ],
    "0c67c231": [
      16
    ],
    "e4da5980": [
      16
    ],
    "1e5606f4": [
      24
    ],
    "df665b48": [
      24
    ],
    "194ca3ba": [
      24
    ],
    "f6249ebc": [
      24
    ],
    "5757ebca": [
      29,
      27,
      9,
      12
    ],
    "3cc0a1b0": [
      29,
      27,
      9,
      12
    ],
    "77cfdb66": [
      29,
      27,
      9,
      12
    ],
    "325232bc": [
      29,
      27,
      9,
      12
    ],
    "5095f098": [
      29,
      27,
      9,
      12
    ],
    "648a5a87": [
      33,
      27,
      9,
      21
    ],
    "cc9be1a2": [
      33,
      27,
      9,
      21
    ],
    "30d109a7": [
      33,
      27,
      9,
      21
    ],
    "2cd71816": [
      33,
      27,
      9,
      21
    ],
    "db3d43ce": [
      33,
      27,
      9,
      21
    ],
    "46493d3e": [
      5,
      27,
      9,
      34
    ],
    "417a0c91": [
      5,
      27,
      9,
      34
    ],
    "2cfc0b38": [
      5,
      27,
      9,
      34
    ],
    "9c8c1742": [
      5,
      27,
      9,
      34
    ],
    "2f817cc6": [
      8,
      27
    ],
    "527842ac": [
      8,
      27
    ],
    "6c73e79a": [
      8,
      27
    ],
    "023b12b4": [
      8,
      27
    ],
    "cb7f73fe": [
      8,
      27
    ],
    "11be01a7": [
      3
    ],
    "f0a741b0": [
      3
    ],
    "57a3abbc": [
      3
    ],
    "63c4046e": [
      3
    ],
    "b932d5d8": [
      3
    ],
    "779f371e": [
      38
    ],
    "6afb7c23": [
      38
    ],
    "1ff6fad0": [
      38
    ],
    "4bd7c769": [
      38
    ],
    "387000ec": [
      38
    ],
    "43a216e4": [
      15,
      27,
      9,
      12,
      11
    ],
    "53c9369c": [
      15,
      27,
      9,
      12,
      11
    ],
    "7862fce8": [
      15,
      27,
      9,
      12,
      11
    ],
    "59006e16": [
      15,
      27,
      9,
      12,
      11
    ],
    "23b3adda": [
      15,
      27,
      9,
      12,
      11
    ],
    "50d485a1": [
      25,
      27,
      9,
      21,
      11
    ],
    "0a6e4300": [
      25,
      27,
      9,
      21,
      11
    ],
    "7ccfafcd": [
      25,
      27,
      9,
      21,
      11
    ],
    "4aab4346": [
      25,
      27,
      9,
      21,
      11
    ],
    "433ff782": [
      25,
      27,
      9,
      21,
      11
    ],
    "9ad400ce": [
      4,
      27,
      9,
      34,
      11
    ],
    "1a2f6238": [
      4,
      27,
      9,
      34,
      11
    ],
    "e50e9a92": [
      4,
      27,
      9,
      34,
      11
    ],
    "00e23032": [
      4,
      27,
      9,
      34,
      11
    ],
    "048ecaf6": [
      4,
      27,
      9,
      34,
      11
    ],
    "56ed2692": [
      10,
      27,
      11
    ],
    "3c353313": [
      10,
      27,
      11
    ],
    "15c4b259": [
      10,
      27,
      11
    ],
    "2ec131e6": [
      10,
      27,
      11
    ],
    "338227b2": [
      10,
      27,
      11
    ],
    "035834e0": [
      36
    ],
    "6184bf30": [
      36
    ],
    "cb520b4e": [
      36
    ],
    "3e72c96a": [
      36
    ],
    "10d45ecc": [
      31,
      26
    ],
    "2978c38d": [
      31,
      26
    ],
    "79385cf4": [
      31,
      26
    ],
    "0d597453": [
      31,
      26
    ],
    "6513d566": [
      31,
      26
    ],
    "2dee2d83": [
      13
    ],
    "2cfd63d1": [
      13
    ],
    "5e8c282b": [
      13
    ],
    "10de1497": [
      13
    ],
    "4a67a09d": [
      13
    ],
    "1ebd4010": [
      30
    ],
    "9c121bb4": [
      30
    ],
    "91a3acc0": [
      30
    ]
  },
  "assetsMapping": {
    "40662714": [
      "a9693bd.js"
    ],
    "7ea24c87": [
      "06873ae.js"
    ],
    "62aadbb5": [
      "10f7f16.js"
    ],
    "12c27f9b": [
      "18b436d.js"
    ],
    "12c2b781": [
      "27076f4.js"
    ],
    "3bc82511": [
      "296531b.js"
    ],
    "d5199c04": [
      "2c6fca8.js"
    ],
    "450ea99f": [
      "4356888.js"
    ],
    "122a4b12": [
      "4e4af3e.js"
    ],
    "450e71b9": [
      "52eda56.js"
    ],
    "474827da": [
      "5692b44.js"
    ],
    "2ce78fbb": [
      "5b856a5.js"
    ],
    "2a130dde": [
      "61bca87.js"
    ],
    "21600ad7": [
      "63fee22.js"
    ],
    "0e01d5e6": [
      "665e510.js"
    ],
    "2afd58e4": [
      "6fe4976.js"
    ],
    "6cb04273": [
      "908cb9e.js"
    ],
    "1a3ae26b": [
      "9606e1b.js"
    ],
    "02431bf2": [
      "9708540.js"
    ],
    "39196fc4": [
      "97d676a.js"
    ],
    "33f6b807": [
      "9f43c5f.js"
    ],
    "6fca0322": [
      "a07282e.js"
    ],
    "efc0f7a2": [
      "a9d4700.js"
    ],
    "f40a6478": [
      "bbfc829.js"
    ],
    "88d51082": [
      "bdeb4aa.js"
    ],
    "085a35c4": [
      "bfb8431.js"
    ],
    "0e020dcc": [
      "c372057.js"
    ],
    "bdcf15dc": [
      "c482ac6.js"
    ],
    "29bd80b0": [
      "c9ad686.js"
    ],
    "17355bee": [
      "c9ebafb.js"
    ],
    "efc087d6": [
      "d8f626b.js"
    ],
    "7496a99b": [
      "dcbced5.js"
    ],
    "37382f10": [
      "de1af1d.js"
    ],
    "4f7aae1e": [
      "e20e1a4.js"
    ],
    "67c13ec2": [
      "ed9b438.js"
    ],
    "d5868d02": [
      "fd4c8d3.js"
    ],
    "2d4a35ec": [
      "ffa1495.js"
    ]
  }
}